AUTHORS
LICENSE
MANIFEST.in
README
domestic-reader
setup.py
domestic/LICENSE
domestic/__init__.py
domestic/domestic.pro
domestic/domestic.py
domestic/res.qrc
domestic/resource.py
domestic/core/__init__.py
domestic/core/database.py
domestic/core/feedsync.py
domestic/core/feedtools.py
domestic/core/settings.py
domestic/dialogs/__init__.py
domestic/dialogs/about.py
domestic/dialogs/downloaddialog.py
domestic/dialogs/feedadd.py
domestic/dialogs/folderadd.py
domestic/dialogs/infodialog.py
domestic/dialogs/progressdialog.py
domestic/images/donate-button.png
domestic/images/loading.gif
domestic/images/rss-icon-128.png
domestic/images/rss-icon.png
domestic/images/icons/apply.png
domestic/images/icons/audio.png
domestic/images/icons/bookmark.png
domestic/images/icons/bookmark_disable.png
domestic/images/icons/button_cancel.png
domestic/images/icons/configure.png
domestic/images/icons/edit_add.png
domestic/images/icons/exit.png
domestic/images/icons/folder_grey.png
domestic/images/icons/folder_grey_open.png
domestic/images/icons/folder_home.png
domestic/images/icons/folder_html.png
domestic/images/icons/folder_tar.png
domestic/images/icons/folder_yellow.png
domestic/images/icons/html.png
domestic/images/icons/info.png
domestic/images/icons/reload.png
domestic/images/icons/trash_empty.png
domestic/images/icons/trash_full.png
domestic/images/icons/web.png
domestic/languages/en_US.qm
domestic/languages/en_US.ts
domestic/languages/tr_TR.qm
domestic/languages/tr_TR.ts
domestic/media/notify.mp3
domestic/widgets/__init__.py
domestic/widgets/firstpage.py
domestic/widgets/lastpage.py
domestic/widgets/menu.py
domestic/widgets/statusbar.py
domestic/widgets/systemtray.py
domestic/widgets/toolbox.py
domestic/widgets/treeitem.py
domestic/widgets/treewidget.py
domestic_reader.egg-info/PKG-INFO
domestic_reader.egg-info/SOURCES.txt
domestic_reader.egg-info/dependency_links.txt
domestic_reader.egg-info/requires.txt
domestic_reader.egg-info/top_level.txt