Metadata-Version: 1.1
Name: domestic-reader
Version: 0.5.1.5
Summary: Free RSS/Atom Reader.
Home-page: https://github.com/mthnzbk/domestic
Author: Metehan Özbek
Author-email: metehan@metehan.us
License: GPL v3
Download-URL: https://pypi.python.org/pypi/domestic-reader
Keywords: PyQt5,feedparser,sqlite,bs4,reader,rss reader,BeautifulSoup
Platform: UNKNOWN
Classifier: Environment :: X11 Applications :: Qt
Classifier: Intended Audience :: End Users/Desktop
Classifier: License :: OSI Approved :: GNU Affero General Public License v3
